<?xml version="1.0" encoding="UTF-8" standalone="no"?>
<!--
  ~ Copyright (c) 2022 LTD Haulmont Samara. All Rights Reserved.
  ~ Haulmont Samara proprietary and confidential.
  ~ Use is subject to license terms.
  -->

<window xmlns="http://schemas.haulmont.com/cuba/window.xsd"
        caption="msg://orderPosting1CEdit.caption"
        class="com.company.thesissummer.web.ui.orderposting1c.OrderPosting1CEdit"
        focusComponent="fieldGroup"
        datasource="orderPosting1CDc"
        messagesPack="com.company.thesissummer.web.ui.orderposting1c">
    <dsContext>
        <datasource id="orderPosting1CDc"
                    class="com.company.thesissummer.entity.table1c.OrderPosting1C"
                    view="orderPosting1C-view"/>
    </dsContext>
    <dialogMode height="600"
                width="800"/>
    <layout expand="windowActions" spacing="true">
        <fieldGroup id="fieldGroup" datasource="orderPosting1CDc">
            <column width="350px">
                <field  property="number"/>
                <field  property="nameofpledger"/>
                <field  property="dogovorwithcollateral"/>
                <field  property="obespecheniye"/>
                <field  property="zalogStoimost"/>
                <field  property="documentUsl"/>
                <field visible="false"  property="orderPosting">
                </field>
            </column>
        </fieldGroup>
        <frame id="windowActions"
               screen="editWindowActions"/>
    </layout>
</window>
